{
    "Keyworded": "1",
    "Period_From": "17/11/2006",
    "Period_To": "1/03/2012",
    "ProjectName": "Great Victoria Desert",
    "ReportDate": "1/03/2012",
    "ReportTitle": "Report on Exploration for Period 17 November 2006 to 16 November 2011, E39/1173, Great Victoria Desert, Mt Margaret, Western Australia",
    "ReportType": "3",
    "SHORT_ABSTRACT": "Final Surrender Report - Great Victoria Desert (17/11/2006 - 01/03/2012)",
    "SUBMIT_DATE": "00:00.0",
    "TENEMENT_LOCATION": "SHAPED",
    "figure_caption_files": [
        "a093015_e39_1173_2011s_15242681.json",
        "a093015_e39_1173_2011s_vr_15239228.json"
    ],
    "full_text_files": [
        "a093015_e39_1173_2011s_15242681.json",
        "a093015_e39_1173_2011s_vr_15239228.json"
    ],
    "pdf_files": [
        "a093015_e39_1173_2011s_15242681.pdf",
        "a093015_e39_1173_2011s_vr_15239228.pdf"
    ]
}